[
  {
    "id": "3d69b6b8-d640-4210-b470-5ec1b24f1330",
    "note": "okay ",
    "amount": "70",
    "createdDate": {
      "_seconds": 1756904344,
      "_nanoseconds": 10291000
    },
    "adminNote": null,
    "paymentDate": null,
    "userId": "HaPLGDLnMdXELy2IaZoV4AjmnXm1",
    "paymentStatus": "approved"
  },
  {
    "id": "52df88aa-79ac-433b-bcf8-5cdfb17674fd",
    "note": "w",
    "amount": "100",
    "createdDate": {
      "_seconds": 1738141727,
      "_nanoseconds": 41949000
    },
    "adminNote": null,
    "paymentDate": null,
    "userId": "iIKsS7N5ZffqU7aGR9Lmd8TQFum2",
    "paymentStatus": "approved"
  },
  {
    "id": "9f005475-e8bb-4305-97f4-61076e94a86d",
    "note": "",
    "amount": "500",
    "createdDate": {
      "_seconds": 1737973898,
      "_nanoseconds": 522932000
    },
    "adminNote": null,
    "paymentDate": null,
    "userId": "ZatcUDJcnUUFpiaGwFKdA3MhVeZ2",
    "paymentStatus": "approved"
  }
]